{
  "cookies": [
    {
      "name": "session-username",
      "value": "standard_user",
      "domain": "www.saucedemo.com",
      "path": "/",
      "expires": 1756315088,
      "httpOnly": false,
      "secure": false,
      "sameSite": "Lax"
    }
  ],
  "origins": [
    {
      "origin": "https://www.saucedemo.com",
      "localStorage": [
        {
          "name": "backtrace-guid",
          "value": "d3f76e8c-ea9d-4a00-b800-5c1360df924e"
        },
        {
          "name": "backtrace-last-active",
          "value": "1756314488473"
        }
      ]
    }
  ]
}